memory_tools_client/__init__.py
memory_tools_client/memory_tools_client.py
memory_tools_client-1.0.12.dist-info/licenses/LICENSE
memory_tools_client-1.0.12.dist-info/METADATA
memory_tools_client-1.0.12.dist-info/WHEEL
memory_tools_client-1.0.12.dist-info/top_level.txt
memory_tools_client-1.0.12.dist-info/RECORD
