Metadata-Version: 2.4
Name: memory-tools-client
Version: 1.0.12
Summary: A Python client for the Memory Tools database.
Home-page: https://github.com/adoboscan21/Memory-Tools-Client-Python3.git
Author: Adonay Boscán
Author-email: adoboscan21@gmail.com
Classifier: Programming Language :: Python :: 3
Classifier: License :: OSI Approved :: MIT License
Classifier: Operating System :: OS Independent
Classifier: Topic :: Database
Classifier: Topic :: Software Development :: Libraries
Requires-Python: >=3.13.5
License-File: LICENSE
Dynamic: author
Dynamic: author-email
Dynamic: classifier
Dynamic: description
Dynamic: description-content-type
Dynamic: home-page
Dynamic: license-file
Dynamic: requires-python
Dynamic: summary
